eksi/__init__.py
eksi/__main__.py
eksi/_version.py
eksi/color.py
eksi/eksi.py
eksi-0.5.0.dist-info/licenses/LICENSE
eksi-0.5.0.dist-info/METADATA
eksi-0.5.0.dist-info/WHEEL
eksi-0.5.0.dist-info/entry_points.txt
eksi-0.5.0.dist-info/top_level.txt
eksi-0.5.0.dist-info/RECORD
