Metadata-Version: 2.4
Name: eksi
Version: 0.5.0
Summary: Komut satırında Ekşisözlük!
Author-email: Furkan Onder <furkanonder@protonmail.com>
Maintainer-email: Furkan Onder <furkanonder@protonmail.com>
License: MIT
Project-URL: Homepage, https://github.com/furkanonder/eksigundem
Project-URL: Documentation, https://github.com/furkanonder/eksigundem#readme
Project-URL: Repository, https://github.com/furkanonder/eksigundem
Project-URL: Bug Reports, https://github.com/furkanonder/eksigundem/issues
Project-URL: Changelog, https://github.com/furkanonder/eksigundem/CHANGELOG.md
Project-URL: Funding, https://github.com/sponsors/furkanonder
Keywords: ekşisözlük,ekşi,eksi,sözlük,eksisozluk,cli,turkish
Classifier: Development Status :: 4 - Beta
Classifier: Intended Audience :: End Users/Desktop
Classifier: Topic :: Utilities
Classifier: Topic :: Internet :: WWW/HTTP :: Browsers
Classifier: Topic :: Terminals
Classifier: Environment :: Console
Classifier: License :: OSI Approved :: MIT License
Classifier: Natural Language :: Turkish
Classifier: Operating System :: OS Independent
Classifier: Programming Language :: Python
Classifier: Programming Language :: Python :: 3 :: Only
Classifier: Programming Language :: Python :: 3.10
Classifier: Programming Language :: Python :: 3.11
Classifier: Programming Language :: Python :: 3.12
Classifier: Programming Language :: Python :: 3.13
Classifier: Programming Language :: Python :: Implementation :: CPython
Classifier: Programming Language :: Python :: Implementation :: PyPy
Requires-Python: >=3.10
License-File: LICENSE
Requires-Dist: beautifulsoup4>=4.12.0
Requires-Dist: lxml>=4.9.0
Provides-Extra: dev
Requires-Dist: pre-commit>=3.0.0; extra == "dev"
Requires-Dist: tox>=4.0.0; extra == "dev"
Requires-Dist: mypy>=1.0.0; extra == "dev"
Requires-Dist: ruff>=0.1.0; extra == "dev"
Dynamic: license-file
